{"stats":{"minecraft:used":{"minecraft:redstone_torch":8,"minecraft:sticky_piston":1,"minecraft:lever":30,"minecraft:dropper":6,"minecraft:command_block":22,"minecraft:iron_block":69,"minecraft:grass_block":21,"minecraft:powered_rail":3,"minecraft:redstone":121,"minecraft:oak_button":1,"minecraft:stone_button":28,"minecraft:sign":19,"minecraft:redstone_block":3,"minecraft:music_disc_wait":4,"minecraft:bedrock":1,"minecraft:white_wool":1,"minecraft:redstone_lamp":10,"minecraft:repeater":17,"minecraft:dirt":58,"minecraft:rail":17,"minecraft:anvil":2,"minecraft:comparator":5,"minecraft:furnace":1,"minecraft:minecart":1,"minecraft:lapis_block":14,"minecraft:stone_pressure_plate":1,"minecraft:music_disc_13":4,"minecraft:observer":1,"minecraft:jukebox":2,"minecraft:obsidian":1},"minecraft:dropped":{"minecraft:oak_button":2},"minecraft:mined":{"minecraft:jukebox":1},"minecraft:custom":{"minecraft:time_since_rest":472736,"minecraft:sprint_one_cm":675,"minecraft:interact_with_furnace":2,"minecraft:inspect_dropper":8,"minecraft:walk_one_cm":173602,"minecraft:drop":2,"minecraft:minecart_one_cm":4809,"minecraft:interact_with_crafting_table":8,"minecraft:fly_one_cm":112288,"minecraft:open_chest":3,"minecraft:crouch_one_cm":3577,"minecraft:play_one_minute":1355510,"minecraft:deaths":1,"minecraft:sneak_time":2861,"minecraft:jump":192,"minecraft:leave_game":29,"minecraft:time_since_death":472695,"minecraft:climb_one_cm":466},"minecraft:picked_up":{"minecraft:redstone_block":1,"minecraft:jukebox":2,"minecraft:music_disc_13":4,"minecraft:bedrock":1,"minecraft:stone_button":6,"minecraft:grass_block":1,"minecraft:redstone":20,"minecraft:dirt":578,"minecraft:sign":12,"minecraft:command_block":2,"minecraft:lever":102,"minecraft:iron_block":1,"minecraft:redstone_torch":3,"minecraft:oak_button":1,"minecraft:music_disc_wait":12,"minecraft:white_wool":1}},"DataVersion":1631}